LICENSE
MANIFEST.in
Readme.md
config.json
requirements.txt
setup.py
article_dataset_builder/S3.py
article_dataset_builder/__init__.py
article_dataset_builder/check_cord19_coverage.py
article_dataset_builder/harvest.py
article_dataset_builder/nlm2tei.py
article_dataset_builder.egg-info/PKG-INFO
article_dataset_builder.egg-info/SOURCES.txt
article_dataset_builder.egg-info/dependency_links.txt
article_dataset_builder.egg-info/requires.txt
article_dataset_builder.egg-info/top_level.txt