Metadata-Version: 2.1
Name: article-dataset-builder
Version: 0.2.6
Summary: Open Access scholar PDF harvester, metadata aggregator and full-text ingester
Home-page: https://github.com/kermitt2/article_dataset_builder
Author: Patrice Lopez
Author-email: patrice.lopez@science-miner.com
Classifier: Programming Language :: Python :: 3.5
Classifier: License :: OSI Approved :: Apache Software License
Classifier: Operating System :: POSIX
Requires-Python: >=3.5
License-File: LICENSE
